django_history_actions-0.1.1.dist-info/METADATA
django_history_actions-0.1.1.dist-info/RECORD
django_history_actions-0.1.1.dist-info/WHEEL
django_history_actions-0.1.1.dist-info/top_level.txt
history_actions/__init__.py
history_actions/admin.py
history_actions/apps.py
history_actions/history_manager.py
history_actions/loader.py
history_actions/mixins.py
history_actions/models.py
history_actions/settings.py
history_actions/migrations/0001_initial.py
history_actions/migrations/__init__.py
