Metadata-Version: 2.1
Name: django-history-actions
Version: 0.1.1
Summary: Django app to track all actions/events accross systems.
Home-page: https://github.com/marcosschroh/django-history-actions
Author: Marcos Schroh
Author-email: schrohm@gmail.com
License: MIT
Keywords: django-history-actions
Platform: UNKNOWN
Classifier: Development Status :: 3 - Alpha
Classifier: Framework :: Django :: 2.0
Classifier: Intended Audience :: Developers
Classifier: License :: OSI Approved :: BSD License
Classifier: Natural Language :: English
Classifier: Programming Language :: Python :: 3
Classifier: Programming Language :: Python :: 3.4
Classifier: Programming Language :: Python :: 3.5
Classifier: Programming Language :: Python :: 3.6
Requires-Dist: django-model-utils (>=2.0)
